calendar_notifications/__init__.py
calendar_notifications/cn_configuration.py
calendar_notifications/main.py
calendar_notifications/bin/notification.mp3
calendar_notifications/bin/reminder.png
calendar_notifications/bin/zoom.png
calendar_notifications/handle_event_start/__init__.py
calendar_notifications/handle_event_start/abstract_event_start_handler.py
calendar_notifications/handle_event_start/zoom_meeting_handler.py
calendar_notifications-0.0.1.dist-info/entry_points.txt
calendar_notifications-0.0.1.dist-info/LICENSE
calendar_notifications-0.0.1.dist-info/WHEEL
calendar_notifications-0.0.1.dist-info/METADATA
calendar_notifications-0.0.1.dist-info/RECORD
