Metadata-Version: 2.1
Name: calendar-notifications
Version: 0.0.1
Summary: Get intrusive calendar notifications on your Mac for Zoom meetings with auto-join button for your Apple computers.
Author-email: Jorrick Sleijster <jorricks3@gmail.com>
Requires-Python: >=3.8
Classifier: Intended Audience :: Information Technology
Classifier: Intended Audience :: Developers
Classifier: Environment :: MacOS X
Classifier: Environment :: MacOS X :: Aqua
Classifier: Environment :: MacOS X :: Carbon
Classifier: Environment :: MacOS X :: Cocoa
Classifier: Topic :: Software Development
Classifier: Topic :: Software Development :: Libraries
Classifier: Topic :: Software Development :: Libraries :: Python Modules
Classifier: Typing :: Typed
Classifier: License :: OSI Approved :: MIT License
Classifier: Programming Language :: Python
Classifier: Programming Language :: Python :: 3
Classifier: Programming Language :: Python :: 3 :: Only
Classifier: Programming Language :: Python :: 3.8
Classifier: Programming Language :: Python :: 3.9
Classifier: Programming Language :: Python :: 3.10
Requires-Dist: ical-library>=0.0.1a1
Requires-Dist: macos-notifications>=0.1.2
Requires-Dist: pre-commit >=2.19.0,<3.0.0 ; extra == "dev"
Requires-Dist: flake8 >=4.0.0,<5.0.0 ; extra == "test"
Requires-Dist: black >= 22.6.0,<23.0.0 ; extra == "test"
Requires-Dist: isort >=5.10.1,<6.0.0 ; extra == "test"
Requires-Dist: mypy ==0.910 ; extra == "test"
Project-URL: Documentation, https://github.com/Jorricks/calendar-notifications
Project-URL: Home, https://github.com/Jorricks/calendar-notifications
Project-URL: Issues, https://github.com/Jorricks/calendar-notifications/issues
Project-URL: PullRequests, https://github.com/Jorricks/calendar-notifications/pulls
Project-URL: Source, https://github.com/Jorricks/calendar-notifications
Provides-Extra: dev
Provides-Extra: test
